p_s_s_p/cmos_cells.v

module BUF(A, Y);
input A;
output Y;
assign Y = A;
endmodule

module NOT(A, Y);
input A;
output Y;
assign Y = ~A;
endmodule

module NAND(A, B, Y);
input A, B;
output Y;
assign Y = ~(A & B);
endmodule

module NOR(A, B, Y);
input A, B;
output Y;
assign Y = ~(A | B);
endmodule

module DFF(C, D, Q);
input C, D;
output reg Q;
always @(posedge C)
	Q <= D;
endmodule

module DFFSR(C, D, Q, S, R);
input C, D, S, R;
output reg Q;
always @(posedge C, posedge S, posedge R)
	if (S)
		Q <= 1'b1;
	else if (R)
		Q <= 1'b0;
	else
		Q <= D;
endmodule // DFFSR

p_s_s_p/parallel_serial_testbench.v
module parallel_serial_testbench(
    input data_out_serial, 
    output reg valid, reset, clk,
    output reg [7:0] data_in_8b
);

    initial begin

      $dumpfile("p_s_s_p.vcd");
      $dumpvars;
        reset <= 1'b1;
        valid <= 1'b0;
        data_in_8b <= 8'h23;
        @(posedge clk);
        reset <= 1'b0;
        @(posedge clk);
        @(posedge clk);
        @(posedge clk);
        @(posedge clk);
        @(posedge clk);
        @(posedge clk);
        @(posedge clk);
        @(posedge clk);
        @(posedge clk);
        @(posedge clk);
        @(posedge clk);
        @(posedge clk);
        valid <= 1;
        data_in_8b <= 8'hAA;
        @(posedge clk);
        @(posedge clk);
        @(posedge clk);
        @(posedge clk);
        @(posedge clk);
        @(posedge clk);
        @(posedge clk);
        @(posedge clk);
        @(posedge clk);
        @(posedge clk);
        @(posedge clk);
        data_in_8b <= 8'hAB;
        @(posedge clk);
        @(posedge clk);
        @(posedge clk);
        @(posedge clk);
        @(posedge clk);
        @(posedge clk);
        @(posedge clk);
        @(posedge clk);
        @(posedge clk);
        @(posedge clk);
        @(posedge clk);        
        
      $finish;

    end

    initial clk <= 0;
    always #2 clk <= ~clk;

endmodule

p_s_s_p/serial_parallel.v
module serial_parallel(
	input clk_f, 
    input clk, 
    input reset, 
    input data_serial_in,
	output reg [7:0] parallel_data,
	output reg valid_out
);

reg active;
reg [2:0] counter;
reg [7:0] data_bus;
reg [7:0] ff_data_bus;
reg ff_data_in;
reg [7:0] BC_counter;

always @(*) begin
    data_bus = ff_data_bus;
    if (reset) begin
        data_bus = 0;
    end
    else begin
        data_bus[counter] = ff_data_in;
    end
end

always @(clk) begin
    ff_data_bus <= data_bus;
    ff_data_in <= data_serial_in;
    if (reset) begin
        counter <= 3'b111;
        BC_counter <= 0;
        active <= 0;
    end    
    else begin
        counter <= counter+1;
    end
end

always @(clk_f) begin
    if (reset) begin
        parallel_data <= 0;
        valid_out <= 0;
    end
    else begin
        // Cuenta la cantida de hex(BC)
        if (parallel_data == 8'hBC) begin
            BC_counter <= BC_counter+1;
        end

        // Revisar la cant. de BC_counter para levantar active
        if (BC_counter > 3) begin
            active <= 1;
        end
        else begin
            active <= 0;
        end

        // Revisar si el dato es valido
        if (active && data_bus != 8'hBC) begin
            valid_out <= 1;
        end
        else begin
            valid_out <= 0;
        end

        // Dato de salida
        if (~active && ~reset) begin
            parallel_data <= 8'hBC;
        end
        else begin
            parallel_data <= data_bus;
        end
    end
end

endmodule

p_s_s_p/parallel_serial.v
module parallel_serial(
    input clk_f, clk, valid, reset,
    input [7:0] data_in_8b,
    output reg data_out_serial
);

reg [2:0] counter;
reg [7:0] data_bus;

always @(clk_f) begin
    if (~valid) begin
        data_bus <= 8'hBC;
    end
    else begin
        data_bus <= data_in_8b;    
    end
end

always @(clk) begin
    if (reset) begin
        counter <= 3'b111;
        data_out_serial <= 0;
    end
    else begin
        data_out_serial <= data_bus[counter];
        counter <= counter-1;
    end    
end

endmodule

p_s_s_p/genClock.v
`timescale 1ns/1ps

module genClock(input clk,
		input 	   reset,
		output reg clk_f,
		output reg clk_2f,
		output reg clk_4f
		);

  always @ (posedge clk) begin
    if (reset==1) begin        
      clk_f <= 1'h0; //reseteando clk
      clk_2f <= 1'h0; //reseteando clk
      clk_4f <= 1'h0; //reseteando clk           
    end else begin         //cambia de alto a bajo o de bajo a alto    
       clk_4f <= ~clk_4f;               
       if (~clk_4f) begin
          clk_2f <= ~clk_2f;
       end
       if (~clk_2f & ~clk_4f) begin 
            clk_f <= ~clk_f;
       end
    end // else: !if(reset==1)
  end // always @ (posedge clk)
   
endmodule // genClock

p_s_s_p/result_testbench.v
`include "cmos_cells.v"
`include "genClock.v"
`include "parallel_serial.v"
`include "serial_parallel.v"
`include "parallel_serial_est.v"
`include "serial_parallel_est.v"
`include "parallel_serial_testbench.v"

module result_testbench();

wire clk, clk_f, clk_2f,clk_4f, valid, reset, data_out_serial, valid_out;
wire [7:0] data_in_8b, parallel_data, parallel_data_est;

   genClock gen_clk(
		 .clk(clk),
		 .reset(reset),
		 .clk_f(clk_f),      //Reloj 4 veces mas lento que clk
		 .clk_2f(clk_2f),
		 .clk_4f(clk_4f)
		    );
   
   parallel_serial p_s_inst(
			 .clk_f(clk_f),      //Reloj 4 veces mas lento que clk 
			 .clk(clk), 
			 .valid(valid), 
			 .reset(reset),
			 .data_in_8b(data_in_8b),
			 .data_out_serial(data_out_serial)
			    );
   
/* -----\/----- EXCLUDED -----\/-----
   parallel_serial_est p_s_inst_est(/-*AUTOINST*-/
				    // Outputs
				    .data_out_serial	(data_out_serial),
				    // Inputs
				    .clk		(clk),
				    .clk_f		(clk_f),
				    .data_in_8b		(data_in_8b[7:0]),
				    .reset		(reset),
				    .valid		(valid));
 -----/\----- EXCLUDED -----/\----- */
   

   serial_parallel s_p_inst(
			    .clk_f(clk_f), 
			    .clk(clk), 
			    .reset(reset), 
			    .data_serial_in(data_out_serial),
			    .parallel_data(parallel_data),
			    .valid_out(valid_out)
			    );
   
   
   parallel_serial_testbench p_s_tb(
				    .clk(clk),
				    .valid(valid), 
				    .reset(reset),
				    .data_in_8b(data_in_8b),
				    .data_out_serial(data_out_serial)
				    );

endmodule // result_testbench

p_s_s_p/p_s_s_p.vcd
$date
	Fri Oct 22 21:49:19 2021
$end
$version
	Icarus Verilog
$end
$timescale
	1ps
$end
$scope module result_testbench $end
$var wire 1 ! valid_out $end
$var wire 1 " valid $end
$var wire 1 # reset $end
$var wire 8 $ parallel_data [7:0] $end
$var wire 1 % data_out_serial $end
$var wire 8 & data_in_8b [7:0] $end
$var wire 1 ' clk_f $end
$var wire 1 ( clk_4f $end
$var wire 1 ) clk_2f $end
$var wire 1 * clk $end
$scope module gen_clk $end
$var wire 1 # reset $end
$var wire 1 * clk $end
$var reg 1 ) clk_2f $end
$var reg 1 ( clk_4f $end
$var reg 1 ' clk_f $end
$upscope $end
$scope module p_s_inst $end
$var wire 1 ' clk_f $end
$var wire 1 " valid $end
$var wire 1 # reset $end
$var wire 8 + data_in_8b [7:0] $end
$var wire 1 * clk $end
$var reg 3 , counter [2:0] $end
$var reg 8 - data_bus [7:0] $end
$var reg 1 % data_out_serial $end
$upscope $end
$scope module p_s_tb $end
$var wire 1 % data_out_serial $end
$var reg 1 * clk $end
$var reg 8 . data_in_8b [7:0] $end
$var reg 1 # reset $end
$var reg 1 " valid $end
$upscope $end
$scope module s_p_inst $end
$var wire 1 * clk $end
$var wire 1 ' clk_f $end
$var wire 1 % data_serial_in $end
$var wire 1 # reset $end
$var reg 8 / BC_counter [7:0] $end
$var reg 1 0 active $end
$var reg 3 1 counter [2:0] $end
$var reg 8 2 data_bus [7:0] $end
$var reg 8 3 ff_data_bus [7:0] $end
$var reg 1 4 ff_data_in $end
$var reg 8 5 parallel_data [7:0] $end
$var reg 1 ! valid_out $end
$upscope $end
$upscope $end
$enddefinitions $end
#0
$dumpvars
bx 5
x4
b0 3
b0 2
b111 1
00
b0 /
b100011 .
bx -
b111 ,
b100011 +
0*
x)
x(
x'
b100011 &
0%
bx $
1#
0"
x!
$end
#2000
b10111100 $
b10111100 5
0!
b10111100 -
0(
0)
0'
0#
04
1*
#4000
b0 1
b110 ,
1%
0*
#6000
b1 /
b10 2
1'
1)
1(
b101 ,
0%
b1 1
14
1*
#8000
b10 1
04
b10 3
b100 ,
1%
0*
#10000
b1010 2
0(
b11 ,
b11 1
14
1*
#12000
b11010 2
b100 1
b1010 3
b10 ,
0*
#14000
b111010 2
0)
1(
b1 ,
b101 1
b11010 3
1*
#16000
b1111010 2
b110 1
b111010 3
b0 ,
0%
0*
#18000
0(
b111 ,
b111 1
04
b1111010 3
1*
#20000
b0 1
b110 ,
1%
0*
#22000
b10 /
0'
1)
1(
b101 ,
0%
b1 1
14
1*
#24000
b10 1
04
b100 ,
1%
0*
#26000
0(
b11 ,
b11 1
14
1*
#28000
b100 1
b10 ,
0*
#30000
0)
1(
b1 ,
b101 1
1*
#32000
b110 1
b0 ,
0%
0*
#34000
0(
b111 ,
b111 1
04
1*
#36000
b0 1
b110 ,
1%
0*
#38000
b11 /
1'
1)
1(
b101 ,
0%
b1 1
14
1*
#40000
b10 1
04
b100 ,
1%
0*
#42000
0(
b11 ,
b11 1
14
1*
#44000
b100 1
b10 ,
0*
#46000
0)
1(
b1 ,
b101 1
1*
#48000
b110 1
b0 ,
0%
0*
#50000
0(
b10101010 &
b10101010 +
b10101010 .
1"
b111 ,
b111 1
04
1*
#52000
b0 1
b110 ,
1%
0*
#54000
b100 /
b10101010 -
0'
1)
1(
b101 ,
0%
b1 1
14
1*
#56000
b10 1
04
b100 ,
1%
0*
#58000
0(
b11 ,
0%
b11 1
14
1*
#60000
b1101010 2
b100 1
04
b10 ,
1%
0*
#62000
0)
1(
b1 ,
0%
b101 1
14
b1101010 3
1*
#64000
b101010 2
b110 1
04
b0 ,
1%
0*
#66000
b10101010 2
0(
b111 ,
0%
b111 1
14
b101010 3
1*
#68000
b0 1
04
b10101010 3
b110 ,
1%
0*
#70000
10
b101 /
1'
1)
1(
b101 ,
0%
b1 1
14
1*
#72000
b10 1
04
b100 ,
1%
0*
#74000
0(
b11 ,
0%
b11 1
14
1*
#76000
b100 1
04
b10 ,
1%
0*
#78000
0)
1(
b1 ,
0%
b101 1
14
1*
#80000
b110 1
04
b0 ,
1%
0*
#82000
0(
b111 ,
0%
b111 1
14
1*
#84000
b0 1
04
b110 ,
1%
0*
#86000
b10101010 $
b10101010 5
1!
b110 /
0'
1)
1(
b101 ,
0%
b1 1
14
1*
#88000
b10 1
04
b100 ,
1%
0*
#90000
0(
b11 ,
0%
b11 1
14
1*
#92000
b100 1
04
b10 ,
1%
0*
#94000
b10101011 &
b10101011 +
b10101011 .
0)
1(
b1 ,
0%
b101 1
14
1*
#96000
b110 1
04
b0 ,
1%
0*
#98000
0(
b111 ,
0%
b111 1
14
1*
#100000
b0 1
04
b110 ,
1%
0*
#102000
b10101011 -
1'
1)
1(
b101 ,
0%
b1 1
14
1*
#104000
b10 1
04
b100 ,
1%
0*
#106000
0(
b11 ,
0%
b11 1
14
1*
#108000
b100 1
04
b10 ,
1%
0*
#110000
0)
1(
b1 ,
0%
b101 1
14
1*
#112000
b110 1
04
b0 ,
1%
0*
#114000
0(
b111 ,
b111 1
14
1*
#116000
b10101011 2
b0 1
b110 ,
0*
#118000
b10101011 $
b10101011 5
0'
1)
1(
b101 ,
0%
b1 1
b10101011 3
1*
#120000
b10 1
04
b100 ,
1%
0*
#122000
0(
b11 ,
0%
b11 1
14
1*
#124000
b100 1
04
b10 ,
1%
0*
#126000
0)
1(
b1 ,
0%
b101 1
14
1*
#128000
b110 1
04
b0 ,
1%
0*
#130000
0(
b111 ,
b111 1
14
1*
#132000
b0 1
b110 ,
0*
#134000
1'
1)
1(
b101 ,
0%
b1 1
1*
#136000
b10 1
04
b100 ,
1%
0*
#138000
0(
b11 ,
0%
b11 1
14
1*
