Rx/tester_rx.v
module tester_rx(
    output reg clk,
    output reg D_0,
    output reg D_1,
    output reg reset,
    output reg enable);


    initial begin

        //A través del tester vamos a enviar diferentes datos al phy, para comprobar que su funcionamiento sea correcto
        //
        $dumpfile("phy_rx.vcd");
		$dumpvars;
		enable <= 'h0;
		reset <= 'h1;
		@(posedge clk);
		reset <= 'h1;
		enable <= 'h1;
		@(posedge clk);
		reset <= 'h0;
		D_0 <= 1'b1;
		D_1 <= 1'b0;
		@(posedge clk);
		D_0 <= 1'b0;
		D_1 <= 1'b1;
		@(posedge clk);
		D_0 <= 1'b1;
		D_1 <= 1'b0;
		@(posedge clk);
		D_0 <= 1'b1;
		D_1 <= 1'b0;
		@(posedge clk);
		D_0 <= 1'b1;
		D_1 <= 1'b0;
		@(posedge clk);
		D_0 <= 1'b0;
		D_1 <= 1'b1;
		@(posedge clk);
		D_0 <= 1'b0;
		D_1 <= 1'b1;
		@(posedge clk);
		D_0 <= 1'b1;
		D_1 <= 1'b0;
		@(posedge clk);
		D_0 <= 1'b1;
		D_1 <= 1'b0;
		@(posedge clk);
		D_0 <= 1'b0;
		D_1 <= 1'b1;

        //A partir de aquí se envían datos 

		@(posedge clk);
		D_0 <= 1'b1;
		D_1 <= 1'b1;
		@(posedge clk);
		D_0 <= 1'b0;
		D_1 <= 1'b0;
		@(posedge clk);
		D_0 <= 1'b1;
		D_1 <= 1'b1;
		@(posedge clk);
		D_0 <= 1'b1;
		D_1 <= 1'b1;

		@(posedge clk);
		D_0 <= 1'b1;
		D_1 <= 1'b1;
		@(posedge clk);
		D_0 <= 1'b1;
		D_1 <= 1'b1;
		@(posedge clk);
		D_0 <= 1'b0;
		D_1 <= 1'b0;
		@(posedge clk);
		D_0 <= 1'b0;
		D_1 <= 1'b0;

		@(posedge clk);
		D_0 <= 1'b1;
		D_1 <= 1'b1;
		@(posedge clk);
		D_0 <= 1'b0;
		D_1 <= 1'b0;
		@(posedge clk);
		D_0 <= 1'b1;
		D_1 <= 1'b1;
		@(posedge clk);
		D_0 <= 1'b1;
		D_1 <= 1'b1;

		@(posedge clk);
		D_0 <= 1'b1;
		D_1 <= 1'b1;
		@(posedge clk);
		D_0 <= 1'b1;
		D_1 <= 1'b1;
		@(posedge clk);
		D_0 <= 1'b0;
		D_1 <= 1'b0;
		@(posedge clk);
		D_0 <= 1'b0;
		D_1 <= 1'b0;

		@(posedge clk);
		D_0 <= 1'b1;
		D_1 <= 1'b1;
		@(posedge clk);
		D_0 <= 1'b0;
		D_1 <= 1'b0;
		@(posedge clk);
		D_0 <= 1'b1;
		D_1 <= 1'b1;
		@(posedge clk);
		D_0 <= 1'b1;
		D_1 <= 1'b1;

		@(posedge clk);
		D_0 <= 1'b1;
		D_1 <= 1'b1;
		@(posedge clk);
		D_0 <= 1'b1;
		D_1 <= 1'b1;
		@(posedge clk);
		D_0 <= 1'b0;
		D_1 <= 1'b0;
		@(posedge clk);
		D_0 <= 1'b0;
		D_1 <= 1'b0;

		@(posedge clk);
		D_0 <= 1'b1;
		D_1 <= 1'b1;
		@(posedge clk);
		D_0 <= 1'b0;
		D_1 <= 1'b0;
		@(posedge clk);
		D_0 <= 1'b1;
		D_1 <= 1'b1;
		@(posedge clk);
		D_0 <= 1'b1;
		D_1 <= 1'b1;

		@(posedge clk);
		D_0 <= 1'b1;
		D_1 <= 1'b1;
		@(posedge clk);
		D_0 <= 1'b1;
		D_1 <= 1'b1;
		@(posedge clk);
		D_0 <= 1'b0;
		D_1 <= 1'b0;
		@(posedge clk);
		D_0 <= 1'b0;
		D_1 <= 1'b0;

		@(posedge clk);
		D_0 <= 1'b0;
		D_1 <= 1'b1;
		@(posedge clk);
		D_0 <= 1'b0;
		D_1 <= 1'b1;
		@(posedge clk);
		D_0 <= 1'b1;
		D_1 <= 1'b1;
		@(posedge clk);
		D_0 <= 1'b1;
		D_1 <= 1'b1;
		@(posedge clk);
		D_0 <= 1'b1;
		D_1 <= 1'b0;
		@(posedge clk);
		D_0 <= 1'b0;
		D_1 <= 1'b1;
		@(posedge clk);
		D_0 <= 1'b0;
		D_1 <= 1'b0;

		@(posedge clk);
		D_0 <= 1'b1;
		D_1 <= 1'b1;
		@(posedge clk);
		D_0 <= 1'b0;
		D_1 <= 1'b0;
		@(posedge clk);
		D_0 <= 1'b1;
		D_1 <= 1'b1;
		@(posedge clk);
		D_0 <= 1'b1;
		D_1 <= 1'b1;

		@(posedge clk);
		D_0 <= 1'b1;
		D_1 <= 1'b1;
		@(posedge clk);
		D_0 <= 1'b1;
		D_1 <= 1'b1;
		@(posedge clk);
		D_0 <= 1'b0;
		D_1 <= 1'b0;
		@(posedge clk);
		D_0 <= 1'b0;
		D_1 <= 1'b0;

		@(posedge clk);
		D_0 <= 1'b1;
		D_1 <= 1'b1;
		@(posedge clk);
		D_0 <= 1'b0;
		D_1 <= 1'b0;
		@(posedge clk);
		D_0 <= 1'b1;
		D_1 <= 1'b1;
		@(posedge clk);
		D_0 <= 1'b1;
		D_1 <= 1'b1;

		@(posedge clk);
		D_0 <= 1'b1;
		D_1 <= 1'b1;
		@(posedge clk);
		D_0 <= 1'b1;
		D_1 <= 1'b1;
		@(posedge clk);
		D_0 <= 1'b0;
		D_1 <= 1'b0;
		@(posedge clk);
		D_0 <= 1'b0;
		D_1 <= 1'b0;

		@(posedge clk);
		D_0 <= 1'b1;
		D_1 <= 1'b1;
		@(posedge clk);
		D_0 <= 1'b0;
		D_1 <= 1'b0;
		@(posedge clk);
		D_0 <= 1'b1;
		D_1 <= 1'b1;
		@(posedge clk);
		D_0 <= 1'b1;
		D_1 <= 1'b1;

		@(posedge clk);
		D_0 <= 1'b1;
		D_1 <= 1'b1;
		@(posedge clk);
		D_0 <= 1'b1;
		D_1 <= 1'b1;
		@(posedge clk);
		D_0 <= 1'b0;
		D_1 <= 1'b0;
		@(posedge clk);
		D_0 <= 1'b0;
		D_1 <= 1'b0;

		@(posedge clk);
		D_0 <= 1'b1;
		D_1 <= 1'b1;
		@(posedge clk);
		D_0 <= 1'b0;
		D_1 <= 1'b0;
		@(posedge clk);
		D_0 <= 1'b1;
		D_1 <= 1'b1;
		@(posedge clk);
		D_0 <= 1'b1;
		D_1 <= 1'b1;
		//$C
		@(posedge clk);
		D_0 <= 1'b1;
		D_1 <= 1'b1;
		@(posedge clk);
		D_0 <= 1'b1;
		D_1 <= 1'b1;
		@(posedge clk);
		D_0 <= 1'b0;
		D_1 <= 1'b0;
		@(posedge clk);
		D_0 <= 1'b0;
		D_1 <= 1'b0;

        //Ahora se prueba con más datos, pero enviando inicialmente datos random
		@(posedge clk);
		D_0 <= $random;
		D_1 <= $random;
		@(posedge clk);
		D_0 <= 1'b0;
		D_1 <= 1'b0;
		@(posedge clk);
		D_0 <= 1'b1;
		D_1 <= 1'b1;
		@(posedge clk);
		D_0 <= 1'b0;
		D_1 <= 1'b0;
		@(posedge clk);
		D_0 <= 1'b1;
		D_1 <= 1'b1;
		@(posedge clk);
		D_0 <= 1'b0;
		D_1 <= 1'b0;
		@(posedge clk);
		D_0 <= 1'b1;
		D_1 <= 1'b1;
		@(posedge clk);
		D_0 <= 1'b0;
		D_1 <= 1'b0;
		@(posedge clk);
		D_0 <= 1'b1;
		D_1 <= 1'b1;
		@(posedge clk);
		D_0 <= 1'b0;
		D_1 <= 1'b0;
		@(posedge clk);
		D_0 <= 1'b1;
		D_1 <= 1'b1;
		@(posedge clk);
		D_0 <= 1'b0;
		D_1 <= 1'b0;
		@(posedge clk);
		D_0 <= 1'b1;
		D_1 <= 1'b1;
		@(posedge clk);
		D_0 <= 1'b0;
		D_1 <= 1'b0;
		@(posedge clk);
		D_0 <= 1'b1;
		D_1 <= 1'b1;
		@(posedge clk);
		D_0 <= 1'b0;
		D_1 <= 1'b0;
		@(posedge clk);
		D_0 <= 1'b1;
		D_1 <= 1'b1;
		@(posedge clk);
		D_0 <= 1'b0;
		D_1 <= 1'b0;
		@(posedge clk);
		D_0 <= 1'b1;
		D_1 <= 1'b1;
		@(posedge clk);
		D_0 <= 1'b0;
		D_1 <= 1'b0;
		@(posedge clk);
		D_0 <= 1'b1;
		D_1 <= 1'b1;
		@(posedge clk);
		D_0 <= 1'b0;
		D_1 <= 1'b0;
		@(posedge clk);
		D_0 <= 1'b1;
		D_1 <= 1'b1;
		@(posedge clk);
		D_0 <= 1'b0;
		D_1 <= 1'b0;
		@(posedge clk);
		D_0 <= 1'b1;
		D_1 <= 1'b1;
		@(posedge clk);
		D_0 <= 1'b0;
		D_1 <= 1'b0;
		@(posedge clk);
		D_0 <= 1'b1;
		D_1 <= 1'b1;
		@(posedge clk);
		D_0 <= 1'b0;
		D_1 <= 1'b0;
		@(posedge clk);
		D_0 <= 1'b1;
		D_1 <= 1'b1;
		@(posedge clk);
		D_0 <= 1'b0;
		D_1 <= 1'b0;
		@(posedge clk);
		D_0 <= 1'b1;
		D_1 <= 1'b1;
		@(posedge clk);
		@(posedge clk);
		@(posedge clk);
		@(posedge clk);
		@(posedge clk);
		@(posedge clk);
		@(posedge clk);
		$finish;
	end

    //Vamos a crear los relojes y hacer el toggle de cada uno de ellos para las pruebas correctas.
	initial	clk <= 0;
	always	#1 clk 	<= ~clk;
    
endmodule

unstripe.v
module unstripe(
		input 		  clk_2f, //Reloj 2f
		input 		  ureset,
		input [31:0] 	  ulane0,
		input [31:0] 	  ulane1,
		input 		  uvalid0,
		input 		  uvalid1,
		
		output reg [31:0] dataOut,
		output reg 	  validOut
		);
   //Definimos algunas variables utiles
   reg [31:0] 			  salidaMux;
   reg [1:0] 			  selector;
   reg 				  valid;

   //Iniciamos la logica del mux
   always @(posedge clk_2f) begin
      if (ureset == 1) begin
	 selector <= 'b00;
      end else begin
	 if (uvalid1 == 1) begin
	    valid <= uvalid1;
	    if (selector == 'b01) begin
	       salidaMux <= ulane1;
	       selector <= selector + 1;
	    end
	    if (selector == 'b11) begin
	       salidaMux <= ulane1;
	       selector <= selector + 1;
	    end else begin
	       valid <= uvalid1;
	       selector <= selector + 1;
	    end
	 end // if (uvalid1 == 1)
	 if (uvalid0 == 1) begin
	    valid <= uvalid0;
	    if (selector == 'b00) begin
	       salidaMux <= ulane0;
	       selector <= selector + 1;
	    end
	    if (selector == 'b10) begin
	       salidaMux <= ulane0;
	       selector <= selector +1;
	    end
	 end else begin // if (uvalid0 == 1)
	    salidaMux <= 'b0;
	    valid <= 'b0;
	    selector <= 0;
	 end // else: !if(uvalid0 == 1)
      end // else: !if(ureset == 1)
   end // always @ (posedge clk_2f)

   //Despues de unstripe, pasamos los resultados a la salida
   always @ (posedge clk_2f) begin
      dataOut <= salidaMux;
      validOut <= valid;
   end
   
endmodule // unstripe

Rx/conv8_32.v
module conv8_32(
		output reg [31:0] out_data32,
		output reg 	  out32,
		input 		  clk_4f,
		input 		  clk_f,
		input 		  reset, 
		input [7:0] 	  in_data8,
		input 		  in8
		);

   reg [2:0] 			  counter = 2'b0;
   reg [7:0] 			  memory_0 = 8'b0;
   reg [15:0] 			  memory_1 = 16'b0;
   reg [23:0] 			  memory_2 = 24'b0;
   reg [31:0] 			  memory_3 = 32'b0;
   reg [31:0] 			  memory_4 = 32'b0;
   reg [31:0] 			  memory_5 = 32'b0;
   reg 				  new_fv = 0;
   reg 				  fv = 0;

   always @(posedge clk_4f)begin
      if (reset == 1)begin
	 counter <= 0;
      end else begin
	 if (in8 == 0) begin
	    if (counter == 4)begin
	       memory_0<=in_data8;
               memory_1<=0;
               memory_2<=0;
               memory_3<=0;
               memory_4<=memory_3;
               new_fv<=1;
	    end
	    if (counter > 0)begin
	       counter <= counter-1;
	    end else begin
	       new_fv <= 0;
	       counter <= 0;
	    end
	 end else begin // if (in8 == 0)
	    if (counter == 4) begin
	       memory_0<=in_data8;
               memory_1<=0;
               memory_2<=0;
               memory_3<=0;
               memory_4<=memory_3;
               counter<=3'b1;
               new_fv<=1;  
	    end else begin
	       memory_0 <= in_data8;
	       memory_1<=in_data8+256*memory_0;
	       memory_2<=in_data8+256*memory_1;
	       memory_3<=in_data8+256*memory_2;
	       
	       counter <= counter+1;
	    end
	 end	
      end // else: !if(reset == 1)
   end // always @ (posedge clk_4f)

   always @(posedge clk_f) begin
      fv <= new_fv;
      memory_5 <= memory_4;
   end

   always @(*) begin
      out_data32 = 32'b0;
      out32 = 0;
      if (reset == 1) begin
	 out32 = 0;
	 out_data32 = 32'b0;
      end else begin
	 out_data32 = memory_5;
	 out32 = fv;
      end
   end // always @ (*)

endmodule // conv8_32

p_s_s_p/serial_parallel.v
module serial_parallel(
	input clk_f, 
    input clk, 
    input reset, 
    input data_serial_in,
	output reg [7:0] parallel_data,
	output reg valid_out
);

reg active;
reg [2:0] counter;
reg [7:0] data_bus;
reg [7:0] ff_data_bus;
reg ff_data_in;
reg [7:0] BC_counter;

always @(*) begin
    data_bus = ff_data_bus;
    if (reset) begin
        data_bus = 0;
    end
    else begin
        data_bus[counter] = ff_data_in;
    end
end

always @(clk) begin
    ff_data_bus <= data_bus;
    ff_data_in <= data_serial_in;
    if (reset) begin
        counter <= 3'b111;
        BC_counter <= 0;
        active <= 0;
    end    
    else begin
        counter <= counter+1;
    end
end

always @(clk_f) begin
    if (reset) begin
        parallel_data <= 0;
        valid_out <= 0;
    end
    else begin
        // Cuenta la cantida de hex(BC)
        if (parallel_data == 8'hBC) begin
            BC_counter <= BC_counter+1;
        end

        // Revisar la cant. de BC_counter para levantar active
        if (BC_counter > 3) begin
            active <= 1;
        end
        else begin
            active <= 0;
        end

        // Revisar si el dato es valido
        if (active && data_bus != 8'hBC) begin
            valid_out <= 1;
        end
        else begin
            valid_out <= 0;
        end

        // Dato de salida
        if (~active && ~reset) begin
            parallel_data <= 8'hBC;
        end
        else begin
            parallel_data <= data_bus;
        end
    end
end

endmodule

Rx/phy_rx.v
`include "unstripe.v"
`include "conv8_32.v"
`include "serial_parallel.v"
`include "genClock.v"

module phy_rx(
    input 	  in_data_serie_0,
    input 	  in_data_serie_1,
    input 	  reset, 
    input 	  valid, 
    input 	  clk, 
    input 	  clk_f,
    input 	  clk_2f, 
    input 	  clk_4f,
    output [31:0] dataOut,
    output 	  validOut
);

   wire [31:0] 	  therTo0, therTo1;
   wire [7:0] 	  ateBit0, ateBit1;
   wire 	  valid0, valid1, valid2, valid3;

    serial_parallel s_p_0(/*AUTOINST*/
			  // Outputs
			  .parallel_data	(ateBit0[7:0]),
			  .valid_out		(valid0),
			  // Inputs
			  .clk_f		(clk_f),
			  .clk			(clk),
			  .reset		(reset),
			  .data_serial_in	(in_data_serie_0));

    serial_parallel s_p_1(/*AUTOINST*/
			  // Outputs
			  .parallel_data	(ateBit1[7:0]),
			  .valid_out		(valid1),
			  // Inputs
			  .clk_f		(clk_f),
			  .clk			(clk),
			  .reset		(reset),
			  .data_serial_in	(in_data_serie_1));

    conv8_32 conv8_32_0(/*AUTOINST*/
			// Outputs
			.out_data32	(therTo0[31:0]),
			.out32		(valid2),
			// Inputs
			.clk_4f		(clk_4f),
			.clk_f		(clk_f),
			.reset		(reset),
			.in_data8	(ateBit0[7:0]),
			.in8		(valid0));
    
    conv8_32 conv8_32_1(/*AUTOINST*/
			// Outputs
			.out_data32	(therTo1[31:0]),
			.out32		(valid3),
			// Inputs
			.clk_4f		(clk_4f),
			.clk_f		(clk_f),
			.reset		(reset),
			.in_data8	(ateBit1[7:0]),
			.in8		(valid1));

    unstripe unstripe_rx(/*AUTOINST*/
			 // Outputs
			 .dataOut		(dataOut[31:0]),
			 .validOut		(validOut),
			 // Inputs
			 .clk_2f		(clk_2f),
			 .ureset		(reset),
			 .ulane0		(therTo0[31:0]),
			 .ulane1		(therTo1[31:0]),
			 .uvalid0		(valid2),
			 .uvalid1		(valid3));
endmodule // phy_rx

p_s_s_p/genClock.v
`timescale 1ns/1ps

module genClock(input clk,
		input 	   reset,
		output reg clk_f,
		output reg clk_2f,
		output reg clk_4f
		);

  always @ (posedge clk) begin
    if (reset==1) begin        
      clk_f <= 1'h0; //reseteando clk
      clk_2f <= 1'h0; //reseteando clk
      clk_4f <= 1'h0; //reseteando clk           
    end else begin         //cambia de alto a bajo o de bajo a alto    
       clk_4f <= ~clk_4f;               
       if (~clk_4f) begin
          clk_2f <= ~clk_2f;
       end
       if (~clk_2f & ~clk_4f) begin 
            clk_f <= ~clk_f;
       end
    end // else: !if(reset==1)
  end // always @ (posedge clk)
   
endmodule // genClock

p_s_s_p/cmos_cells.v

module BUF(A, Y);
input A;
output Y;
assign Y = A;
endmodule

module NOT(A, Y);
input A;
output Y;
assign Y = ~A;
endmodule

module NAND(A, B, Y);
input A, B;
output Y;
assign Y = ~(A & B);
endmodule

module NOR(A, B, Y);
input A, B;
output Y;
assign Y = ~(A | B);
endmodule

module DFF(C, D, Q);
input C, D;
output reg Q;
always @(posedge C)
	Q <= D;
endmodule

module DFFSR(C, D, Q, S, R);
input C, D, S, R;
output reg Q;
always @(posedge C, posedge S, posedge R)
	if (S)
		Q <= 1'b1;
	else if (R)
		Q <= 1'b0;
	else
		Q <= D;
endmodule // DFFSR

Rx/phy_rx.vcd
$date
	Fri Oct 22 20:48:29 2021
$end
$version
	Icarus Verilog
$end
$timescale
	1ps
$end
$scope module BUF $end
$var wire 1 ! A $end
$var wire 1 " Y $end
$upscope $end
$scope module DFF $end
$var wire 1 # C $end
$var wire 1 $ D $end
$var reg 1 % Q $end
$upscope $end
$scope module DFFSR $end
$var wire 1 & C $end
$var wire 1 ' D $end
$var wire 1 ( R $end
$var wire 1 ) S $end
$var reg 1 * Q $end
$upscope $end
$scope module NAND $end
$var wire 1 + A $end
$var wire 1 , B $end
$var wire 1 - Y $end
$upscope $end
$scope module NOR $end
$var wire 1 . A $end
$var wire 1 / B $end
$var wire 1 0 Y $end
$upscope $end
$scope module NOT $end
$var wire 1 1 A $end
$var wire 1 2 Y $end
$upscope $end
$scope module genClock $end
$var wire 1 3 clk $end
$var wire 1 4 reset $end
$var reg 1 5 clk_2f $end
$var reg 1 6 clk_4f $end
$var reg 1 7 clk_f $end
$upscope $end
$scope module phy_rx $end
$var wire 1 8 clk $end
$var wire 1 9 clk_2f $end
$var wire 1 : clk_4f $end
$var wire 1 ; clk_f $end
$var wire 1 < in_data_serie_0 $end
$var wire 1 = in_data_serie_1 $end
$var wire 1 > reset $end
$var wire 1 ? valid $end
$var wire 1 @ validOut $end
$var wire 1 A valid3 $end
$var wire 1 B valid2 $end
$var wire 1 C valid1 $end
$var wire 1 D valid0 $end
$var wire 32 E therTo1 [31:0] $end
$var wire 32 F therTo0 [31:0] $end
$var wire 32 G dataOut [31:0] $end
$var wire 8 H ateBit1 [7:0] $end
$var wire 8 I ateBit0 [7:0] $end
$scope module conv8_32_0 $end
$var wire 1 : clk_4f $end
$var wire 1 ; clk_f $end
$var wire 1 > reset $end
$var wire 8 J in_data8 [7:0] $end
$var wire 1 D in8 $end
$var reg 3 K counter [2:0] $end
$var reg 1 L fv $end
$var reg 8 M memory_0 [7:0] $end
$var reg 16 N memory_1 [15:0] $end
$var reg 24 O memory_2 [23:0] $end
$var reg 32 P memory_3 [31:0] $end
$var reg 32 Q memory_4 [31:0] $end
$var reg 32 R memory_5 [31:0] $end
$var reg 1 S new_fv $end
$var reg 1 B out32 $end
$var reg 32 T out_data32 [31:0] $end
$upscope $end
$scope module conv8_32_1 $end
$var wire 1 : clk_4f $end
$var wire 1 ; clk_f $end
$var wire 1 > reset $end
$var wire 8 U in_data8 [7:0] $end
$var wire 1 C in8 $end
$var reg 3 V counter [2:0] $end
$var reg 1 W fv $end
$var reg 8 X memory_0 [7:0] $end
$var reg 16 Y memory_1 [15:0] $end
$var reg 24 Z memory_2 [23:0] $end
$var reg 32 [ memory_3 [31:0] $end
$var reg 32 \ memory_4 [31:0] $end
$var reg 32 ] memory_5 [31:0] $end
$var reg 1 ^ new_fv $end
$var reg 1 A out32 $end
$var reg 32 _ out_data32 [31:0] $end
$upscope $end
$scope module s_p_0 $end
$var wire 1 8 clk $end
$var wire 1 ; clk_f $end
$var wire 1 < data_serial_in $end
$var wire 1 > reset $end
$var reg 8 ` BC_counter [7:0] $end
$var reg 1 a active $end
$var reg 3 b counter [2:0] $end
$var reg 8 c data_bus [7:0] $end
$var reg 8 d ff_data_bus [7:0] $end
$var reg 1 e ff_data_in $end
$var reg 8 f parallel_data [7:0] $end
$var reg 1 D valid_out $end
$upscope $end
$scope module s_p_1 $end
$var wire 1 8 clk $end
$var wire 1 ; clk_f $end
$var wire 1 = data_serial_in $end
$var wire 1 > reset $end
$var reg 8 g BC_counter [7:0] $end
$var reg 1 h active $end
$var reg 3 i counter [2:0] $end
$var reg 8 j data_bus [7:0] $end
$var reg 8 k ff_data_bus [7:0] $end
$var reg 1 l ff_data_in $end
$var reg 8 m parallel_data [7:0] $end
$var reg 1 C valid_out $end
$upscope $end
$scope module unstripe_rx $end
$var wire 1 9 clk_2f $end
$var wire 32 n ulane0 [31:0] $end
$var wire 32 o ulane1 [31:0] $end
$var wire 1 > ureset $end
$var wire 1 B uvalid0 $end
$var wire 1 A uvalid1 $end
$var reg 32 p dataOut [31:0] $end
$var reg 32 q salidaMux [31:0] $end
$var reg 2 r selector [1:0] $end
$var reg 1 s valid $end
$var reg 1 @ validOut $end
$upscope $end
$upscope $end
$scope module tester_rx $end
$var reg 1 t D_0 $end
$var reg 1 u D_1 $end
$var reg 1 v clk $end
$var reg 1 w enable $end
$var reg 1 x reset $end
$upscope $end
$enddefinitions $end
#0
$dumpvars
1x
0w
0v
xu
xt
xs
bx r
bx q
bx p
b0 o
b0 n
bx m
zl
bx k
bx j
bx i
0h
bx g
bx f
ze
bx d
bx c
bx b
0a
bx `
b0 _
0^
b0 ]
b0 \
b0 [
b0 Z
b0 Y
b0 X
0W
b0 V
bx U
b0 T
0S
b0 R
b0 Q
b0 P
b0 O
b0 N
b0 M
0L
b0 K
bx J
bx I
bx H
bx G
b0 F
b0 E
0D
0C
0B
0A
x@
z?
z>
z=
z<
z;
z:
z9
z8
x7
x6
x5
z4
z3
z2
z1
x0
z/
z.
x-
z,
z+
x*
z)
z(
z'
z&
x%
z$
z#
z"
z!
$end
#1000
1w
1v
#2000
0v
#3000
0u
1t
0x
1v
#4000
0v
#5000
1u
0t
1v
#6000
0v
#7000
0u
1t
1v
#8000
0v
#9000
1v
#10000
0v
#11000
1v
#12000
0v
#13000
1u
0t
1v
#14000
0v
#15000
1v
#16000
0v
#17000
0u
1t
1v
#18000
0v
#19000
1v
#20000
0v
#21000
1u
0t
1v
#22000
0v
#23000
1t
1v
#24000
0v
#25000
0u
0t
1v
#26000
0v
#27000
1u
1t
1v
#28000
0v
#29000
1v
#30000
0v
#31000
1v
#32000
0v
#33000
1v
#34000
0v
#35000
0u
0t
1v
#36000
0v
#37000
1v
#38000
0v
#39000
1u
1t
1v
#40000
0v
#41000
0u
0t
1v
#42000
0v
#43000
1u
1t
1v
#44000
0v
#45000
1v
#46000
0v
#47000
1v
#48000
0v
#49000
1v
#50000
0v
#51000
0u
0t
1v
#52000
0v
#53000
1v
#54000
0v
#55000
1u
1t
1v
#56000
0v
#57000
0u
0t
1v
#58000
0v
#59000
1u
1t
1v
#60000
0v
#61000
1v
#62000
0v
#63000
1v
#64000
0v
#65000
1v
#66000
0v
#67000
0u
0t
1v
#68000
0v
#69000
1v
#70000
0v
#71000
1u
1t
1v
#72000
0v
#73000
0u
0t
1v
#74000
0v
#75000
1u
1t
1v
#76000
0v
#77000
1v
#78000
0v
#79000
1v
#80000
0v
#81000
1v
#82000
0v
#83000
0u
0t
1v
#84000
0v
#85000
1v
#86000
0v
#87000
1u
1v
#88000
0v
#89000
1v
#90000
0v
#91000
1t
1v
#92000
0v
#93000
1v
#94000
0v
#95000
0u
1v
#96000
0v
#97000
1u
0t
1v
#98000
0v
#99000
0u
1v
#100000
0v
#101000
1u
1t
1v
#102000
0v
#103000
0u
0t
1v
#104000
0v
#105000
1u
1t
1v
#106000
0v
#107000
1v
#108000
0v
#109000
1v
#110000
0v
#111000
1v
#112000
0v
#113000
0u
0t
1v
#114000
0v
#115000
1v
#116000
0v
#117000
1u
1t
1v
#118000
0v
#119000
0u
0t
1v
#120000
0v
#121000
1u
1t
1v
#122000
0v
#123000
1v
#124000
0v
#125000
1v
#126000
0v
#127000
1v
#128000
0v
#129000
0u
0t
1v
#130000
0v
#131000
1v
#132000
0v
#133000
1u
1t
1v
#134000
0v
#135000
0u
0t
1v
#136000
0v
#137000
1u
1t
1v
#138000
0v
#139000
1v
#140000
0v
#141000
1v
#142000
0v
#143000
1v
#144000
0v
#145000
0u
0t
1v
#146000
0v
#147000
1v
#148000
0v
#149000
1u
1t
1v
#150000
0v
#151000
0u
0t
1v
#152000
0v
#153000
1u
1t
1v
#154000
0v
#155000
1v
#156000
0v
#157000
1v
#158000
0v
#159000
1v
#160000
0v
#161000
0u
0t
1v
#162000
0v
#163000
1v
#164000
0v
#165000
1u
1v
#166000
0v
#167000
0u
1v
#168000
0v
#169000
1u
1t
1v
#170000
0v
#171000
0u
0t
1v
#172000
0v
#173000
1u
1t
1v
#174000
0v
#175000
0u
0t
1v
#176000
0v
#177000
1u
1t
1v
#178000
0v
#179000
0u
0t
1v
#180000
0v
#181000
1u
1t
1v
#182000
0v
#183000
0u
0t
1v
#184000
0v
#185000
1u
1t
1v
#186000
0v
#187000
0u
0t
1v
#188000
0v
#189000
1u
1t
1v
#190000
0v
#191000
0u
0t
1v
#192000
0v
#193000
1u
1t
1v
#194000
0v
#195000
0u
0t
1v
#196000
0v
#197000
1u
1t
1v
#198000
0v
#199000
0u
0t
1v
#200000
0v
#201000
1u
1t
1v
#202000
0v
#203000
0u
0t
1v
#204000
0v
#205000
1u
1t
1v
#206000
0v
#207000
0u
0t
1v
#208000
0v
#209000
1u
1t
1v
#210000
0v
#211000
0u
0t
1v
#212000
0v
#213000
1u
1t
1v
#214000
0v
#215000
0u
0t
1v
#216000
0v
#217000
1u
1t
1v
#218000
0v
#219000
0u
0t
1v
#220000
0v
#221000
1u
1t
1v
#222000
0v
#223000
0u
0t
1v
#224000
0v
#225000
1u
1t
1v
