Tx/probadorTx.v
module probadorTx(
		  input 	    out_tx_serial_0,
		  input 	    out_tx_serial_1,
		  output reg 	    reset,
		  output reg 	    clk,
		  output reg [31:0] data_in_flops,
		  output reg 	    validIn	  
		); 

	initial begin
	   $dumpfile("TxTest");	// Nombre de archivo del "dump"
	   $dumpvars;			// Directiva para "dumpear" variables
	   {reset} = 'b0; 	// A todos los bits, asigna un tipo bit con valor 0.
	   repeat (5) begin
	      @(posedge clk);
	   end
	   validIn <= 1;
	   repeat (1600) begin		//
              @(posedge clk);	// Espera/sincroniza con el flanco positivo del reloj
	      data_in_flops <= data_in_flops - 1;
	   end
	   @(posedge clk);	
	   {reset} <= 'b0;	// Asigna un tipo bit con valor 0, de tamano N
	   $finish;			// Termina de almacenar senales
	end // initial begin

	// Reloj
   initial	clk 	<= 0;			// Valor inicial al reloj, sino siempre sera indeterminado
   initial	validIn <= 0;
   initial      reset <= 1;
   initial      data_in_flops  <= {32{1'b1}};      
   
   
   always #100  clk 	<= ~clk;
   always #200 reset <= 0;
   
endmodule // probadorTx

p_s_s_p/parallel_serial.v
module parallel_serial(
    input clk_f, clk, valid, reset,
    input [7:0] data_in_8b,
    output reg data_out_serial
);

reg [2:0] counter;
reg [7:0] data_bus;

always @(clk_f) begin
    if (~valid) begin
        data_bus <= 8'hBC;
    end
    else begin
        data_bus <= data_in_8b;    
    end
end

always @(clk) begin
    if (reset) begin
        counter <= 3'b111;
        data_out_serial <= 0;
    end
    else begin
        data_out_serial <= data_bus[counter];
        counter <= counter-1;
    end    
end

endmodule

conv32_8.v
module conv32_8(
		output reg [7:0] out_data8,
		output reg 	 out8,
		input 		 clk_4f,
		input 		 clk_f,
		input 		 reset,
		input [31:0] 	 in_data32,
		input 		 in32
		);


   reg [1:0] 			 contador=2'b0;
   
   always @(posedge clk_4f) begin
      if(reset==1||in32==0) begin
	 contador<=0;
      end else begin 
	 contador<=contador+1;
      end
   end

   always @(*) begin
      out_data8=8'b0;
      out8=0;
      if (in32==0||reset==1) begin
	 out8=0;
	 out_data8=8'b0;
      end else if (contador==0) begin
	 out_data8=in_data32[31:24];
	 out8=1;
      end else if (contador==1) begin
	 out_data8=in_data32[23:16];
	 out8=1;
      end else if (contador==2) begin
	 out_data8=in_data32[15:8];
	 out8=1;
      end else if (contador==3) begin
	 out_data8=in_data32[7:0];
	 out8=1;
      end
   end

endmodule // conv32_8

stripe.v
module stripe(
	      input 		clk_2f, //Reloj 2f
	      input [31:0] 	dataIn,
	      input 		validIn,
	      input 		reset,

	      output reg [31:0] lane0,
	      output reg [31:0] lane1,
	      output reg 	valid0,
	      output reg 	valid1
	      );
   //Definimos valores inicales en cero
   reg [31:0] 		 valorL0 = 32'b0;
   reg [31:0] 		 valorL1 = 32'b0;
   reg 			 valorV0 = 0;
   reg 			 valorV1 = 0;
   reg 			 valorV = 0;
   //Creamos algunas variables utiles
   reg 			 selector;
   reg 			 valorS;
   reg [31:0] 		 temp;
   

   // Iniciamos con la logica del circuito
   always @ (posedge clk_2f) begin
      valorL0 <= lane0;
      valorL1 <= lane1;
      valorV0 <= valid0;
      valorV1 <= valid1;
      valorV <= validIn;
      valorS <= selector;
   end

   always @ (*) begin
      lane0 = valorL0;
      lane1 = valorL1;
      valid0 = valorV0;
      valid1 = valorV1;
      selector = valorS;
      //Revisamos la condicion de Reset
      if (reset) begin
	 valid0 = 0;
	 valid1 = 0;
	 selector = 0;
      end else begin
	 if (~valorV) begin
	    if (validIn) begin
	       valid0 = 1;
	       valid1 = 0;
	       selector = 1;
	    end else begin
	       valid0 = 0;
	       valid1 = 0;
	    end
	 end // if (~valorV)
	 if (validIn) begin
	    if (~valorS) begin
	       lane0= dataIn;
	       lane1 = valorL1;
	       selector = 1;
	    end else begin
	       lane0 = valorL0;
	       lane1 = dataIn;
	       selector = 0;
	       valid1 = 1;
	    end
	 end // if (validIn)
	 if (valorV) begin
	    if (~validIn) begin
	       if (~selector) begin
		  valid0 = 0;
		  lane1 = valorL1;
		  selector = 0;
	       end else begin
		  valid1 = 0;
		  lane0 = valorL0;
		  selector = 0;
	       end
	    end // if (~validIn)
	 end // if (valorV)
	 if (~valid0) begin
	    lane0 = temp;
	 end
	 if (~valid1) begin
	    lane1 = temp;
	 end
      end // else: !if(reset)
   end // always @ (*)
    
endmodule // stripe

Tx/phy_tx.v
module phy_tx(
	input 	     clk_f, clk_2f, clk_4f,
	input [31:0] data_in_flops,
	input 	     validIn,
	input 	     reset, 
	output reg   out_tx_serial_0,
	output reg   out_tx_serial_1
	      );
   wire [31:0] 	     lane0, lane1;
   wire [7:0] 	     ateBit0, ateBit1;
   wire 	     valid0, valid1, valid2, valid3;
   
 	     
   
   stripe striping_tx(/*AUTOINST*/
		      // Outputs
		      .lane0		(lane0[31:0]),
		      .lane1		(lane1[31:0]),
		      .valid0		(valid0),
		      .valid1		(valid1),
		      // Inputs
		      .clk_2f		(clk_2f),
		      .dataIn		(data_in_flops[31:0]),
		      .validIn		(validIn),
		      .reset		(reset));
   
   conv32_8 conversion0_tx(/*AUTOINST*/
			   // Outputs
			   .out_data8		(ateBit0[7:0]),
			   .out8		(valid2),
			   // Inputs
			   .clk_4f		(clk_4f),
			   .clk_f		(clk_f),
			   .reset		(reset),
			   .in_data32		(lane0[31:0]),
			   .in32		(valid0));
   conv32_8 conversion1_tx(/*AUTOINST*/
			   // Outputs
			   .out_data8		(ateBit1[7:0]),
			   .out8		(valid3),
			   // Inputs
			   .clk_4f		(clk_4f),
			   .clk_f		(clk_f),
			   .reset		(reset),
			   .in_data32		(lane1[31:0]),
			   .in32		(valid1));
   
   parallel_serial pToS0_tx(/*AUTOINST*/
			    // Outputs
			    .data_out_serial	(data_out_serial_0),
			    // Inputs
			    .clk_f		(clk_f),
			    .clk		(clk),
			    .valid		(valid2),
			    .reset		(reset),
			    .data_in_8b		(ateBit0[7:0]));
   parallel_serial pToS1_tx(/*AUTOINST*/
			    // Outputs
			    .data_out_serial	(data_out_serial_1),
			    // Inputs
			    .clk_f		(clk_f),
			    .clk		(clk),
			    .valid		(valid3),
			    .reset		(reset),
			    .data_in_8b		(ateBit1[7:0]));
endmodule // phy_tx

p_s_s_p/genClock.v
`timescale 1ns/1ps

module genClock(input clk,
		input 	   reset,
		output reg clk_f,
		output reg clk_2f,
		output reg clk_4f
		);

  always @ (posedge clk) begin
    if (reset==1) begin        
      clk_f <= 1'h0; //reseteando clk
      clk_2f <= 1'h0; //reseteando clk
      clk_4f <= 1'h0; //reseteando clk           
    end else begin         //cambia de alto a bajo o de bajo a alto    
       clk_4f <= ~clk_4f;               
       if (~clk_4f) begin
          clk_2f <= ~clk_2f;
       end
       if (~clk_2f & ~clk_4f) begin 
            clk_f <= ~clk_f;
       end
    end // else: !if(reset==1)
  end // always @ (posedge clk)
   
endmodule // genClock

Tx/BancoPruebaTx.v
`timescale 	1ns				/ 100ps
// escala	unidad temporal (valor de "#1") / precision
// includes de archivos de verilog
`include "cmos_cells.v"
`include "stripe.v"
`include "conv32_8.v"
`include "genClock.v"
`include "parallel_serial.v"
`include "phy_tx.v"
`include "probadorTx.v"

module BancoPruebaTx; // Testbench para striping

   wire clk_f, clk_2f, clk_4f, clk, reset, validIn, out_tx_serial_0, out_tx_serial_1;
   wire [31:0] data_in_flops;

   // Generador Relojes
   genClock generador(/*AUTOINST*/
		      // Outputs
		      .clk_f		(clk_f),
		      .clk_2f		(clk_2f),
		      .clk_4f		(clk_4f),
		      // Inputs
		      .clk		(clk),
		      .reset		(reset));
   
   // Descripcion conductual del circuito
   phy_tx transmision(/*AUTOINST*/
		      // Outputs
		      .out_tx_serial_0	(out_tx_serial_0),
		      .out_tx_serial_1	(out_tx_serial_1),
		      // Inputs
		      .clk_f		(clk_f),
		      .clk_2f		(clk_2f),
		      .clk_4f		(clk_4f),
		      .data_in_flops	(data_in_flops[31:0]),
		      .validIn		(validIn),
		      .reset		(reset));
   
   // Probador: generador de senales y monitor
   probadorTx tester(/*AUTOINST*/
		     // Outputs
		     .reset		(reset),
		     .clk		(clk),
		     .data_in_flops	(data_in_flops[31:0]),
		     .validIn		(validIn),
		     // Inputs
		     .out_tx_serial_0	(out_tx_serial_0),
		     .out_tx_serial_1	(out_tx_serial_1));
   
   
endmodule // BancoPruebas

p_s_s_p/cmos_cells.v

module BUF(A, Y);
input A;
output Y;
assign Y = A;
endmodule

module NOT(A, Y);
input A;
output Y;
assign Y = ~A;
endmodule

module NAND(A, B, Y);
input A, B;
output Y;
assign Y = ~(A & B);
endmodule

module NOR(A, B, Y);
input A, B;
output Y;
assign Y = ~(A | B);
endmodule

module DFF(C, D, Q);
input C, D;
output reg Q;
always @(posedge C)
	Q <= D;
endmodule

module DFFSR(C, D, Q, S, R);
input C, D, S, R;
output reg Q;
always @(posedge C, posedge S, posedge R)
	if (S)
		Q <= 1'b1;
	else if (R)
		Q <= 1'b0;
	else
		Q <= D;
endmodule // DFFSR

Tx/TxTest.vcd
$date
	Thu Oct 21 22:32:13 2021
$end
$version
	Icarus Verilog
$end
$timescale
	1ps
$end
$scope module BUF $end
$var wire 1 ! A $end
$var wire 1 " Y $end
$upscope $end
$scope module BancoPruebaTx $end
$var wire 1 # validIn $end
$var wire 1 $ reset $end
$var wire 1 % out_tx_serial_1 $end
$var wire 1 & out_tx_serial_0 $end
$var wire 32 ' data_in_flops [31:0] $end
$var wire 1 ( clk_f $end
$var wire 1 ) clk_4f $end
$var wire 1 * clk_2f $end
$var wire 1 + clk $end
$scope module generador $end
$var wire 1 $ reset $end
$var wire 1 + clk $end
$var reg 1 * clk_2f $end
$var reg 1 ) clk_4f $end
$var reg 1 ( clk_f $end
$upscope $end
$scope module tester $end
$var wire 1 % out_tx_serial_1 $end
$var wire 1 & out_tx_serial_0 $end
$var reg 1 + clk $end
$var reg 32 , data_in_flops [31:0] $end
$var reg 1 $ reset $end
$var reg 1 # validIn $end
$upscope $end
$scope module transmision $end
$var wire 1 - clk $end
$var wire 1 * clk_2f $end
$var wire 1 ) clk_4f $end
$var wire 1 ( clk_f $end
$var wire 32 . data_in_flops [31:0] $end
$var wire 1 $ reset $end
$var wire 1 # validIn $end
$var wire 1 / valid3 $end
$var wire 1 0 valid2 $end
$var wire 1 1 valid1 $end
$var wire 1 2 valid0 $end
$var wire 32 3 lane1 [31:0] $end
$var wire 32 4 lane0 [31:0] $end
$var wire 1 5 data_out_serial_1 $end
$var wire 1 6 data_out_serial_0 $end
$var wire 8 7 ateBit1 [7:0] $end
$var wire 8 8 ateBit0 [7:0] $end
$var reg 1 & out_tx_serial_0 $end
$var reg 1 % out_tx_serial_1 $end
$scope module conversion0_tx $end
$var wire 1 ) clk_4f $end
$var wire 1 ( clk_f $end
$var wire 1 $ reset $end
$var wire 32 9 in_data32 [31:0] $end
$var wire 1 2 in32 $end
$var reg 2 : contador [1:0] $end
$var reg 1 0 out8 $end
$var reg 8 ; out_data8 [7:0] $end
$upscope $end
$scope module conversion1_tx $end
$var wire 1 ) clk_4f $end
$var wire 1 ( clk_f $end
$var wire 1 $ reset $end
$var wire 32 < in_data32 [31:0] $end
$var wire 1 1 in32 $end
$var reg 2 = contador [1:0] $end
$var reg 1 / out8 $end
$var reg 8 > out_data8 [7:0] $end
$upscope $end
$scope module pToS0_tx $end
$var wire 1 - clk $end
$var wire 1 ( clk_f $end
$var wire 8 ? data_in_8b [7:0] $end
$var wire 1 $ reset $end
$var wire 1 0 valid $end
$var reg 3 @ counter [2:0] $end
$var reg 8 A data_bus [7:0] $end
$var reg 1 6 data_out_serial $end
$upscope $end
$scope module pToS1_tx $end
$var wire 1 - clk $end
$var wire 1 ( clk_f $end
$var wire 8 B data_in_8b [7:0] $end
$var wire 1 $ reset $end
$var wire 1 / valid $end
$var reg 3 C counter [2:0] $end
$var reg 8 D data_bus [7:0] $end
$var reg 1 5 data_out_serial $end
$upscope $end
$scope module striping_tx $end
$var wire 1 * clk_2f $end
$var wire 32 E dataIn [31:0] $end
$var wire 1 $ reset $end
$var wire 1 # validIn $end
$var reg 32 F lane0 [31:0] $end
$var reg 32 G lane1 [31:0] $end
$var reg 1 H selector $end
$var reg 32 I temp [31:0] $end
$var reg 1 2 valid0 $end
$var reg 1 1 valid1 $end
$var reg 32 J valorL0 [31:0] $end
$var reg 32 K valorL1 [31:0] $end
$var reg 1 L valorS $end
$var reg 1 M valorV $end
$var reg 1 N valorV0 $end
$var reg 1 O valorV1 $end
$upscope $end
$upscope $end
$upscope $end
$scope module DFF $end
$var wire 1 P C $end
$var wire 1 Q D $end
$var reg 1 R Q $end
$upscope $end
$scope module DFFSR $end
$var wire 1 S C $end
$var wire 1 T D $end
$var wire 1 U R $end
$var wire 1 V S $end
$var reg 1 W Q $end
$upscope $end
$scope module NAND $end
$var wire 1 X A $end
$var wire 1 Y B $end
$var wire 1 Z Y $end
$upscope $end
$scope module NOR $end
$var wire 1 [ A $end
$var wire 1 \ B $end
$var wire 1 ] Y $end
$upscope $end
$scope module NOT $end
$var wire 1 ^ A $end
$var wire 1 _ Y $end
$upscope $end
$enddefinitions $end
#0
$dumpvars
z_
z^
x]
z\
z[
xZ
zY
zX
xW
zV
zU
zT
zS
xR
zQ
zP
0O
0N
0M
xL
b0 K
b0 J
bx I
0H
b0 G
b0 F
b11111111111111111111111111111111 E
bx D
bx C
b0 B
bx A
bx @
b0 ?
b0 >
b0 =
b0 <
b0 ;
b0 :
b0 9
b0 8
b0 7
x6
x5
b0 4
b0 3
02
01
00
0/
b11111111111111111111111111111111 .
z-
b11111111111111111111111111111111 ,
0+
x*
x)
x(
b11111111111111111111111111111111 '
x&
x%
1$
0#
z"
z!
$end
#100000
b10111100 D
b10111100 A
0)
0*
0(
1+
#200000
bx 3
bx <
bx G
bx 4
bx 9
bx F
xH
0+
0$
#300000
bx K
bx J
1(
1*
1)
1+
#400000
0+
#500000
0)
1+
#600000
0+
#700000
0*
1)
1+
#800000
0+
#900000
1/
b11111111 7
b11111111 >
b11111111 B
10
bx 8
bx ;
bx ?
11
b11111111111111111111111111111111 3
b11111111111111111111111111111111 <
b11111111111111111111111111111111 G
0H
12
0)
1#
1+
#1000000
0+
#1100000
b11111111111111111111111111111110 4
b11111111111111111111111111111110 9
b11111111111111111111111111111110 F
b11111111 D
bx A
0L
1M
1O
1N
b11111111111111111111111111111111 K
b1 :
b1 =
10
b11111111 8
b11111111 ;
b11111111 ?
1/
b11111111 7
b11111111 >
b11111111 B
1H
11
12
b11111111111111111111111111111111 3
b11111111111111111111111111111111 <
b11111111111111111111111111111111 G
b11111111111111111111111111111110 '
b11111111111111111111111111111110 ,
b11111111111111111111111111111110 .
b11111111111111111111111111111110 E
0(
1*
1)
1+
#1200000
0+
#1300000
10
b11111111 8
b11111111 ;
b11111111 ?
1H
b11111111111111111111111111111101 4
b11111111111111111111111111111101 9
b11111111111111111111111111111101 F
0)
b11111111111111111111111111111101 '
b11111111111111111111111111111101 ,
b11111111111111111111111111111101 .
b11111111111111111111111111111101 E
1+
#1400000
0+
#1500000
1/
b11111111 7
b11111111 >
b11111111 B
b10 =
b10 :
10
b11111111 8
b11111111 ;
b11111111 ?
1H
b11111111111111111111111111111100 4
b11111111111111111111111111111100 9
b11111111111111111111111111111100 F
b11111111111111111111111111111100 '
b11111111111111111111111111111100 ,
b11111111111111111111111111111100 .
b11111111111111111111111111111100 E
0*
1)
1+
#1600000
0+
#1700000
10
b11111111 8
b11111111 ;
b11111111 ?
1H
b11111111111111111111111111111011 4
b11111111111111111111111111111011 9
b11111111111111111111111111111011 F
0)
b11111111111111111111111111111011 '
b11111111111111111111111111111011 ,
b11111111111111111111111111111011 .
b11111111111111111111111111111011 E
1+
#1800000
0+
#1900000
b11111111111111111111111111111010 3
b11111111111111111111111111111010 <
b11111111111111111111111111111010 G
1/
b11111010 7
b11111010 >
b11111010 B
b11111111 A
1L
b11111111111111111111111111111011 J
b11 :
b11 =
10
b11111011 8
b11111011 ;
b11111011 ?
0H
b11111111111111111111111111111011 4
b11111111111111111111111111111011 9
b11111111111111111111111111111011 F
b11111111111111111111111111111010 '
b11111111111111111111111111111010 ,
b11111111111111111111111111111010 .
b11111111111111111111111111111010 E
1(
1*
1)
1+
#2000000
0+
#2100000
1/
b11111001 7
b11111001 >
b11111001 B
0H
b11111111111111111111111111111001 3
b11111111111111111111111111111001 <
b11111111111111111111111111111001 G
0)
b11111111111111111111111111111001 '
b11111111111111111111111111111001 ,
b11111111111111111111111111111001 .
b11111111111111111111111111111001 E
1+
#2200000
0+
#2300000
10
b11111111 8
b11111111 ;
b11111111 ?
b0 =
b0 :
1/
b11111111 7
b11111111 >
b11111111 B
0H
b11111111111111111111111111111000 3
b11111111111111111111111111111000 <
b11111111111111111111111111111000 G
b11111111111111111111111111111000 '
b11111111111111111111111111111000 ,
b11111111111111111111111111111000 .
b11111111111111111111111111111000 E
0*
1)
1+
#2400000
0+
#2500000
1/
b11111111 7
b11111111 >
b11111111 B
0H
b11111111111111111111111111110111 3
b11111111111111111111111111110111 <
b11111111111111111111111111110111 G
0)
b11111111111111111111111111110111 '
b11111111111111111111111111110111 ,
b11111111111111111111111111110111 .
b11111111111111111111111111110111 E
1+
#2600000
0+
#2700000
b11111111111111111111111111110110 4
b11111111111111111111111111110110 9
b11111111111111111111111111110110 F
10
b11111111 8
b11111111 ;
b11111111 ?
0L
b11111111111111111111111111110111 K
b1 :
b1 =
1/
b11111111 7
b11111111 >
b11111111 B
1H
b11111111111111111111111111110111 3
b11111111111111111111111111110111 <
b11111111111111111111111111110111 G
b11111111111111111111111111110110 '
b11111111111111111111111111110110 ,
b11111111111111111111111111110110 .
b11111111111111111111111111110110 E
0(
1*
1)
1+
#2800000
0+
#2900000
10
b11111111 8
b11111111 ;
b11111111 ?
1H
b11111111111111111111111111110101 4
b11111111111111111111111111110101 9
b11111111111111111111111111110101 F
0)
b11111111111111111111111111110101 '
b11111111111111111111111111110101 ,
b11111111111111111111111111110101 .
b11111111111111111111111111110101 E
1+
#3000000
0+
#3100000
1/
b11111111 7
b11111111 >
b11111111 B
b10 =
b10 :
10
b11111111 8
b11111111 ;
b11111111 ?
1H
b11111111111111111111111111110100 4
b11111111111111111111111111110100 9
b11111111111111111111111111110100 F
b11111111111111111111111111110100 '
b11111111111111111111111111110100 ,
b11111111111111111111111111110100 .
b11111111111111111111111111110100 E
0*
1)
1+
#3200000
0+
#3300000
10
b11111111 8
b11111111 ;
b11111111 ?
1H
b11111111111111111111111111110011 4
b11111111111111111111111111110011 9
b11111111111111111111111111110011 F
0)
b11111111111111111111111111110011 '
b11111111111111111111111111110011 ,
b11111111111111111111111111110011 .
b11111111111111111111111111110011 E
1+
#3400000
0+
#3500000
b11111111111111111111111111110010 3
b11111111111111111111111111110010 <
b11111111111111111111111111110010 G
1/
b11110010 7
b11110010 >
b11110010 B
1L
b11111111111111111111111111110011 J
b11 :
b11 =
10
b11110011 8
b11110011 ;
b11110011 ?
0H
b11111111111111111111111111110011 4
b11111111111111111111111111110011 9
b11111111111111111111111111110011 F
b11111111111111111111111111110010 '
b11111111111111111111111111110010 ,
b11111111111111111111111111110010 .
b11111111111111111111111111110010 E
1(
1*
1)
1+
#3600000
0+
#3700000
1/
b11110001 7
b11110001 >
b11110001 B
0H
b11111111111111111111111111110001 3
b11111111111111111111111111110001 <
b11111111111111111111111111110001 G
0)
b11111111111111111111111111110001 '
b11111111111111111111111111110001 ,
b11111111111111111111111111110001 .
b11111111111111111111111111110001 E
1+
#3800000
0+
#3900000
10
b11111111 8
b11111111 ;
b11111111 ?
b0 =
b0 :
1/
b11111111 7
b11111111 >
b11111111 B
0H
b11111111111111111111111111110000 3
b11111111111111111111111111110000 <
b11111111111111111111111111110000 G
b11111111111111111111111111110000 '
b11111111111111111111111111110000 ,
b11111111111111111111111111110000 .
b11111111111111111111111111110000 E
0*
1)
1+
#4000000
0+
#4100000
1/
b11111111 7
b11111111 >
b11111111 B
0H
b11111111111111111111111111101111 3
b11111111111111111111111111101111 <
b11111111111111111111111111101111 G
0)
b11111111111111111111111111101111 '
b11111111111111111111111111101111 ,
b11111111111111111111111111101111 .
b11111111111111111111111111101111 E
1+
#4200000
0+
#4300000
b11111111111111111111111111101110 4
b11111111111111111111111111101110 9
b11111111111111111111111111101110 F
10
b11111111 8
b11111111 ;
b11111111 ?
0L
b11111111111111111111111111101111 K
b1 :
b1 =
1/
b11111111 7
b11111111 >
b11111111 B
1H
b11111111111111111111111111101111 3
b11111111111111111111111111101111 <
b11111111111111111111111111101111 G
b11111111111111111111111111101110 '
b11111111111111111111111111101110 ,
b11111111111111111111111111101110 .
b11111111111111111111111111101110 E
0(
1*
1)
1+
#4400000
0+
#4500000
10
b11111111 8
b11111111 ;
b11111111 ?
1H
b11111111111111111111111111101101 4
b11111111111111111111111111101101 9
b11111111111111111111111111101101 F
0)
b11111111111111111111111111101101 '
b11111111111111111111111111101101 ,
b11111111111111111111111111101101 .
b11111111111111111111111111101101 E
1+
#4600000
0+
#4700000
1/
b11111111 7
b11111111 >
b11111111 B
b10 =
b10 :
10
b11111111 8
b11111111 ;
b11111111 ?
1H
b11111111111111111111111111101100 4
b11111111111111111111111111101100 9
b11111111111111111111111111101100 F
b11111111111111111111111111101100 '
b11111111111111111111111111101100 ,
b11111111111111111111111111101100 .
b11111111111111111111111111101100 E
0*
1)
1+
#4800000
0+
#4900000
10
b11111111 8
b11111111 ;
b11111111 ?
1H
b11111111111111111111111111101011 4
b11111111111111111111111111101011 9
b11111111111111111111111111101011 F
0)
b11111111111111111111111111101011 '
b11111111111111111111111111101011 ,
b11111111111111111111111111101011 .
b11111111111111111111111111101011 E
1+
#5000000
0+
#5100000
b11111111111111111111111111101010 3
b11111111111111111111111111101010 <
b11111111111111111111111111101010 G
1/
b11101010 7
b11101010 >
b11101010 B
1L
b11111111111111111111111111101011 J
b11 :
b11 =
10
b11101011 8
b11101011 ;
b11101011 ?
0H
b11111111111111111111111111101011 4
b11111111111111111111111111101011 9
b11111111111111111111111111101011 F
b11111111111111111111111111101010 '
b11111111111111111111111111101010 ,
b11111111111111111111111111101010 .
b11111111111111111111111111101010 E
1(
1*
1)
1+
#5200000
0+
#5300000
1/
b11101001 7
b11101001 >
b11101001 B
0H
b11111111111111111111111111101001 3
b11111111111111111111111111101001 <
b11111111111111111111111111101001 G
0)
b11111111111111111111111111101001 '
b11111111111111111111111111101001 ,
b11111111111111111111111111101001 .
b11111111111111111111111111101001 E
1+
#5400000
0+
#5500000
10
b11111111 8
b11111111 ;
b11111111 ?
b0 =
b0 :
1/
b11111111 7
b11111111 >
b11111111 B
0H
b11111111111111111111111111101000 3
b11111111111111111111111111101000 <
b11111111111111111111111111101000 G
b11111111111111111111111111101000 '
b11111111111111111111111111101000 ,
b11111111111111111111111111101000 .
b11111111111111111111111111101000 E
0*
1)
1+
#5600000
0+
#5700000
1/
b11111111 7
b11111111 >
b11111111 B
0H
b11111111111111111111111111100111 3
b11111111111111111111111111100111 <
b11111111111111111111111111100111 G
0)
b11111111111111111111111111100111 '
b11111111111111111111111111100111 ,
b11111111111111111111111111100111 .
b11111111111111111111111111100111 E
1+
#5800000
0+
#5900000
b11111111111111111111111111100110 4
b11111111111111111111111111100110 9
b11111111111111111111111111100110 F
10
b11111111 8
b11111111 ;
b11111111 ?
0L
b11111111111111111111111111100111 K
b1 :
b1 =
1/
b11111111 7
b11111111 >
b11111111 B
1H
b11111111111111111111111111100111 3
b11111111111111111111111111100111 <
b11111111111111111111111111100111 G
b11111111111111111111111111100110 '
b11111111111111111111111111100110 ,
b11111111111111111111111111100110 .
b11111111111111111111111111100110 E
0(
1*
1)
1+
#6000000
0+
#6100000
10
b11111111 8
b11111111 ;
b11111111 ?
1H
b11111111111111111111111111100101 4
b11111111111111111111111111100101 9
b11111111111111111111111111100101 F
0)
b11111111111111111111111111100101 '
b11111111111111111111111111100101 ,
b11111111111111111111111111100101 .
b11111111111111111111111111100101 E
1+
#6200000
0+
#6300000
1/
b11111111 7
b11111111 >
b11111111 B
b10 =
b10 :
10
b11111111 8
b11111111 ;
b11111111 ?
1H
b11111111111111111111111111100100 4
b11111111111111111111111111100100 9
b11111111111111111111111111100100 F
b11111111111111111111111111100100 '
b11111111111111111111111111100100 ,
b11111111111111111111111111100100 .
b11111111111111111111111111100100 E
0*
1)
1+
#6400000
0+
#6500000
10
b11111111 8
b11111111 ;
b11111111 ?
1H
b11111111111111111111111111100011 4
b11111111111111111111111111100011 9
b11111111111111111111111111100011 F
0)
b11111111111111111111111111100011 '
b11111111111111111111111111100011 ,
b11111111111111111111111111100011 .
b11111111111111111111111111100011 E
1+
#6600000
0+
#6700000
b11111111111111111111111111100010 3
b11111111111111111111111111100010 <
b11111111111111111111111111100010 G
1/
b11100010 7
b11100010 >
b11100010 B
1L
b11111111111111111111111111100011 J
b11 :
b11 =
10
b11100011 8
b11100011 ;
b11100011 ?
0H
b11111111111111111111111111100011 4
b11111111111111111111111111100011 9
b11111111111111111111111111100011 F
b11111111111111111111111111100010 '
b11111111111111111111111111100010 ,
b11111111111111111111111111100010 .
b11111111111111111111111111100010 E
1(
1*
1)
1+
#6800000
0+
#6900000
1/
b11100001 7
b11100001 >
b11100001 B
0H
b11111111111111111111111111100001 3
b11111111111111111111111111100001 <
b11111111111111111111111111100001 G
0)
b11111111111111111111111111100001 '
b11111111111111111111111111100001 ,
b11111111111111111111111111100001 .
b11111111111111111111111111100001 E
1+
#7000000
0+
#7100000
10
b11111111 8
b11111111 ;
b11111111 ?
b0 =
b0 :
1/
b11111111 7
b11111111 >
b11111111 B
0H
b11111111111111111111111111100000 3
b11111111111111111111111111100000 <
b11111111111111111111111111100000 G
b11111111111111111111111111100000 '
b11111111111111111111111111100000 ,
b11111111111111111111111111100000 .
b11111111111111111111111111100000 E
0*
1)
1+
#7200000
0+
#7300000
1/
b11111111 7
b11111111 >
b11111111 B
0H
b11111111111111111111111111011111 3
b11111111111111111111111111011111 <
b11111111111111111111111111011111 G
0)
b11111111111111111111111111011111 '
b11111111111111111111111111011111 ,
b11111111111111111111111111011111 .
b11111111111111111111111111011111 E
1+
#7400000
0+
#7500000
b11111111111111111111111111011110 4
b11111111111111111111111111011110 9
b11111111111111111111111111011110 F
10
b11111111 8
b11111111 ;
b11111111 ?
0L
b11111111111111111111111111011111 K
b1 :
b1 =
1/
b11111111 7
b11111111 >
b11111111 B
1H
b11111111111111111111111111011111 3
b11111111111111111111111111011111 <
b11111111111111111111111111011111 G
b11111111111111111111111111011110 '
b11111111111111111111111111011110 ,
b11111111111111111111111111011110 .
b11111111111111111111111111011110 E
0(
1*
1)
1+
#7600000
0+
#7700000
10
b11111111 8
b11111111 ;
b11111111 ?
1H
b11111111111111111111111111011101 4
b11111111111111111111111111011101 9
b11111111111111111111111111011101 F
0)
b11111111111111111111111111011101 '
b11111111111111111111111111011101 ,
b11111111111111111111111111011101 .
b11111111111111111111111111011101 E
1+
#7800000
0+
#7900000
1/
b11111111 7
b11111111 >
b11111111 B
b10 =
b10 :
10
b11111111 8
b11111111 ;
b11111111 ?
1H
b11111111111111111111111111011100 4
b11111111111111111111111111011100 9
b11111111111111111111111111011100 F
b11111111111111111111111111011100 '
b11111111111111111111111111011100 ,
b11111111111111111111111111011100 .
b11111111111111111111111111011100 E
0*
1)
1+
#8000000
0+
#8100000
10
b11111111 8
b11111111 ;
b11111111 ?
1H
b11111111111111111111111111011011 4
b11111111111111111111111111011011 9
b11111111111111111111111111011011 F
0)
b11111111111111111111111111011011 '
b11111111111111111111111111011011 ,
b11111111111111111111111111011011 .
b11111111111111111111111111011011 E
1+
#8200000
0+
#8300000
b11111111111111111111111111011010 3
b11111111111111111111111111011010 <
b11111111111111111111111111011010 G
1/
b11011010 7
b11011010 >
b11011010 B
1L
b11111111111111111111111111011011 J
b11 :
b11 =
10
b11011011 8
b11011011 ;
b11011011 ?
0H
b11111111111111111111111111011011 4
b11111111111111111111111111011011 9
b11111111111111111111111111011011 F
b11111111111111111111111111011010 '
b11111111111111111111111111011010 ,
b11111111111111111111111111011010 .
b11111111111111111111111111011010 E
1(
1*
1)
1+
#8400000
0+
#8500000
1/
b11011001 7
b11011001 >
b11011001 B
0H
b11111111111111111111111111011001 3
b11111111111111111111111111011001 <
b11111111111111111111111111011001 G
0)
b11111111111111111111111111011001 '
b11111111111111111111111111011001 ,
b11111111111111111111111111011001 .
b11111111111111111111111111011001 E
1+
#8600000
0+
#8700000
10
b11111111 8
b11111111 ;
b11111111 ?
b0 =
b0 :
1/
b11111111 7
b11111111 >
b11111111 B
0H
b11111111111111111111111111011000 3
b11111111111111111111111111011000 <
b11111111111111111111111111011000 G
b11111111111111111111111111011000 '
b11111111111111111111111111011000 ,
b11111111111111111111111111011000 .
b11111111111111111111111111011000 E
0*
1)
1+
#8800000
0+
#8900000
1/
b11111111 7
b11111111 >
b11111111 B
0H
b11111111111111111111111111010111 3
b11111111111111111111111111010111 <
b11111111111111111111111111010111 G
0)
b11111111111111111111111111010111 '
b11111111111111111111111111010111 ,
b11111111111111111111111111010111 .
b11111111111111111111111111010111 E
1+
#9000000
0+
#9100000
b11111111111111111111111111010110 4
b11111111111111111111111111010110 9
b11111111111111111111111111010110 F
10
b11111111 8
b11111111 ;
b11111111 ?
0L
b11111111111111111111111111010111 K
b1 :
b1 =
1/
b11111111 7
b11111111 >
b11111111 B
1H
b11111111111111111111111111010111 3
b11111111111111111111111111010111 <
b11111111111111111111111111010111 G
b11111111111111111111111111010110 '
b11111111111111111111111111010110 ,
b11111111111111111111111111010110 .
b11111111111111111111111111010110 E
0(
1*
1)
1+
#9200000
0+
