conv32_8.v
module conv32_8(
		output reg [7:0] out_data8,
		output reg 	 out8,
		input 		 clk_4f,
		input 		 clk_f,
		input 		 reset,
		input [31:0] 	 in_data32,
		input 		 in32
		);


   reg [1:0] 			 contador=2'b0;
   
   always @(posedge clk_4f) begin
      if(reset==1||in32==0) begin
	 contador<=0;
      end else begin 
	 contador<=contador+1;
      end
   end

   always @(*) begin
      out_data8=8'b0;
      out8=0;
      if (in32==0||reset==1) begin
	 out8=0;
	 out_data8=8'b0;
      end else if (contador==0) begin
	 out_data8=in_data32[31:24];
	 out8=1;
      end else if (contador==1) begin
	 out_data8=in_data32[23:16];
	 out8=1;
      end else if (contador==2) begin
	 out_data8=in_data32[15:8];
	 out8=1;
      end else if (contador==3) begin
	 out_data8=in_data32[7:0];
	 out8=1;
      end
   end

endmodule // conv32_8

32_8/tester.v
module tester(
	input [7:0]			out_data8,
	input               out8,
	output reg			clk,clk_4f,clk_f,
	output reg [31:0]	in_data32,
	output reg 			reset,
	output reg          in32);
	
initial begin
		$dumpfile("32_8.vcd");	
		$dumpvars;
		in32 <= 0; //valor inicial para in
		in_data32 <= 32'b0; //valor inicial para la entrada
		reset <= 'h0;
		//enb <= 'h0;
		@(posedge clk_f);
		reset <= 'h1;
		//enb <= 'h1;
		in32 <= 1;
		@(posedge clk_f);
		reset <= 'h0;
		//enb <= 'h1;
		@(posedge clk_f);
		in_data32 <= 32'hFFFFFFFF;
		@(posedge clk_f);
		in_data32 <= 32'hDDDDDDDD;
		@(posedge clk_f);
		in_data32 <= 32'h00000003;
		@(posedge clk_f);
		@(posedge clk_f);
		@(posedge clk_f);
		@(posedge clk_f);
		@(posedge clk_f);
		@(posedge clk_f);
		@(posedge clk_f);
		@(posedge clk_f);
		@(posedge clk_f);
		@(posedge clk_f);
		@(posedge clk_f);
		@(posedge clk_f);
		@(posedge clk_f);
		@(posedge clk_f);
		@(posedge clk_f);
		@(posedge clk_f);
		@(posedge clk_f);
		@(posedge clk_f);
		$finish;
	end
	
	initial	clk <= 0; 
	always	#1 clk 	<= ~clk; //toggle cada 1ns
	
	initial	clk_f <= 0; 
	always	#128 clk_f 	<= ~clk_f; //toggle cada 128ns
	
	initial	clk_4f <= 0; 
	always	#32 clk_4f 	<= ~clk_4f; //toggle cada 32ns
	
	
endmodule

32_8/testbench.v
`timescale 1ns/ 100ps

`include "conv32_8.v"
`include "tester.v"

module testbench;
	wire reset, clk, clk_f, clk_4f;
	wire [31:0] in_data32;
	wire [7:0] out_data8;
	wire out8, in32;

	tester test2
		(/*AUTOINST*/
		 // Outputs
		 .clk			(clk),
		 .clk_4f		(clk_4f),
		 .clk_f			(clk_f),
		 .in_data32		(in_data32[31:0]),
		 .reset			(reset),
		 .in32			(in32),
		 // Inputs
		 .out_data8		(out_data8[7:0]),
		 .out8			(out8));

	conv32_8 coduct_328
		(/*AUTOINST*/
		 // Outputs
		 .out_data8		(out_data8[7:0]),
		 .out8			(out8),
		 // Inputs
		 .clk_4f		(clk_4f),
		 .clk_f			(clk_f),
		 .reset			(reset),
		 .in_data32		(in_data32[31:0]),
		 .in32			(in32));


endmodule

32_8/32_8.vcd
$date
	Tue Oct  5 17:23:12 2021
$end
$version
	Icarus Verilog
$end
$timescale
	100ps
$end
$scope module testbench $end
$var wire 1 ! reset $end
$var wire 8 " out_data8 [7:0] $end
$var wire 1 # out8 $end
$var wire 32 $ in_data32 [31:0] $end
$var wire 1 % in32 $end
$var wire 1 & clk_f $end
$var wire 1 ' clk_4f $end
$var wire 1 ( clk $end
$scope module coduct_328 $end
$var wire 1 ! reset $end
$var wire 32 ) in_data32 [31:0] $end
$var wire 1 % in32 $end
$var wire 1 & clk_f $end
$var wire 1 ' clk_4f $end
$var reg 2 * contador [1:0] $end
$var reg 1 # out8 $end
$var reg 8 + out_data8 [7:0] $end
$upscope $end
$scope module test2 $end
$var wire 1 # out8 $end
$var wire 8 , out_data8 [7:0] $end
$var reg 1 ( clk $end
$var reg 1 ' clk_4f $end
$var reg 1 & clk_f $end
$var reg 1 % in32 $end
$var reg 32 - in_data32 [31:0] $end
$var reg 1 ! reset $end
$upscope $end
$upscope $end
$enddefinitions $end
#0
$dumpvars
b0 -
b0 ,
b0 +
b0 *
b0 )
0(
0'
0&
0%
b0 $
0#
b0 "
0!
$end
#10
1(
#20
0(
#30
1(
#40
0(
#50
1(
#60
0(
#70
1(
#80
0(
#90
1(
#100
0(
#110
1(
#120
0(
#130
1(
#140
0(
#150
1(
#160
0(
#170
1(
#180
0(
#190
1(
#200
0(
#210
1(
#220
0(
#230
1(
#240
0(
#250
1(
#260
0(
#270
1(
#280
0(
#290
1(
#300
0(
#310
1(
#320
0(
1'
#330
1(
#340
0(
#350
1(
#360
0(
#370
1(
#380
0(
#390
1(
#400
0(
#410
1(
#420
0(
#430
1(
#440
0(
#450
1(
#460
0(
#470
1(
#480
0(
#490
1(
#500
0(
#510
1(
#520
0(
#530
1(
#540
0(
#550
1(
#560
0(
#570
1(
#580
0(
#590
1(
#600
0(
#610
1(
#620
0(
#630
1(
#640
0(
0'
#650
1(
#660
0(
#670
1(
#680
0(
#690
1(
#700
0(
#710
1(
#720
0(
#730
1(
#740
0(
#750
1(
#760
0(
#770
1(
#780
0(
#790
1(
#800
0(
#810
1(
#820
0(
#830
1(
#840
0(
#850
1(
#860
0(
#870
1(
#880
0(
#890
1(
#900
0(
#910
1(
#920
0(
#930
1(
#940
0(
#950
1(
#960
0(
1'
#970
1(
#980
0(
#990
1(
#1000
0(
#1010
1(
#1020
0(
#1030
1(
#1040
0(
#1050
1(
#1060
0(
#1070
1(
#1080
0(
#1090
1(
#1100
0(
#1110
1(
#1120
0(
#1130
1(
#1140
0(
#1150
1(
#1160
0(
#1170
1(
#1180
0(
#1190
1(
#1200
0(
#1210
1(
#1220
0(
#1230
1(
#1240
0(
#1250
1(
#1260
0(
#1270
1(
#1280
1%
1!
0(
0'
1&
#1290
1(
#1300
0(
#1310
1(
#1320
0(
#1330
1(
#1340
0(
#1350
1(
#1360
0(
#1370
1(
#1380
0(
#1390
1(
#1400
0(
#1410
1(
#1420
0(
#1430
1(
#1440
0(
#1450
1(
#1460
0(
#1470
1(
#1480
0(
#1490
1(
#1500
0(
#1510
1(
#1520
0(
#1530
1(
#1540
0(
#1550
1(
#1560
0(
#1570
1(
#1580
0(
#1590
1(
#1600
0(
1'
#1610
1(
#1620
0(
#1630
1(
#1640
0(
#1650
1(
#1660
0(
#1670
1(
#1680
0(
#1690
1(
#1700
0(
#1710
1(
#1720
0(
#1730
1(
#1740
0(
#1750
1(
#1760
0(
#1770
1(
#1780
0(
#1790
1(
#1800
0(
#1810
1(
#1820
0(
#1830
1(
#1840
0(
#1850
1(
#1860
0(
#1870
1(
#1880
0(
#1890
1(
#1900
0(
#1910
1(
#1920
0(
0'
#1930
1(
#1940
0(
#1950
1(
#1960
0(
#1970
1(
#1980
0(
#1990
1(
#2000
0(
#2010
1(
#2020
0(
#2030
1(
#2040
0(
#2050
1(
#2060
0(
#2070
1(
#2080
0(
#2090
1(
#2100
0(
#2110
1(
#2120
0(
#2130
1(
#2140
0(
#2150
1(
#2160
0(
#2170
1(
#2180
0(
#2190
1(
#2200
0(
#2210
1(
#2220
0(
#2230
1(
#2240
0(
1'
#2250
1(
#2260
0(
#2270
1(
#2280
0(
#2290
1(
#2300
0(
#2310
1(
#2320
0(
#2330
1(
#2340
0(
#2350
1(
#2360
0(
#2370
1(
#2380
0(
#2390
1(
#2400
0(
#2410
1(
#2420
0(
#2430
1(
#2440
0(
#2450
1(
#2460
0(
#2470
1(
#2480
0(
#2490
1(
#2500
0(
#2510
1(
#2520
0(
#2530
1(
#2540
0(
#2550
1(
#2560
0(
0'
0&
#2570
1(
#2580
0(
#2590
1(
#2600
0(
#2610
1(
#2620
0(
#2630
1(
#2640
0(
#2650
1(
#2660
0(
#2670
1(
#2680
0(
#2690
1(
#2700
0(
#2710
1(
#2720
0(
#2730
1(
#2740
0(
#2750
1(
#2760
0(
#2770
1(
#2780
0(
#2790
1(
#2800
0(
#2810
1(
#2820
0(
#2830
1(
#2840
0(
#2850
1(
#2860
0(
#2870
1(
#2880
0(
1'
#2890
1(
#2900
0(
#2910
1(
#2920
0(
#2930
1(
#2940
0(
#2950
1(
#2960
0(
#2970
1(
#2980
0(
#2990
1(
#3000
0(
#3010
1(
#3020
0(
#3030
1(
#3040
0(
#3050
1(
#3060
0(
#3070
1(
#3080
0(
#3090
1(
#3100
0(
#3110
1(
#3120
0(
#3130
1(
#3140
0(
#3150
1(
#3160
0(
#3170
1(
#3180
0(
#3190
1(
#3200
0(
0'
#3210
1(
#3220
0(
#3230
1(
#3240
0(
#3250
1(
#3260
0(
#3270
1(
#3280
0(
#3290
1(
#3300
0(
#3310
1(
#3320
0(
#3330
1(
#3340
0(
#3350
1(
#3360
0(
#3370
1(
#3380
0(
#3390
1(
#3400
0(
#3410
1(
#3420
0(
#3430
1(
#3440
0(
#3450
1(
#3460
0(
#3470
1(
#3480
0(
#3490
1(
#3500
0(
#3510
1(
#3520
0(
1'
#3530
1(
#3540
0(
#3550
1(
#3560
0(
#3570
1(
#3580
0(
#3590
1(
#3600
0(
#3610
1(
#3620
0(
#3630
1(
#3640
0(
#3650
1(
#3660
0(
#3670
1(
#3680
0(
#3690
1(
#3700
0(
#3710
1(
#3720
0(
#3730
1(
#3740
0(
#3750
1(
#3760
0(
#3770
1(
#3780
0(
#3790
1(
#3800
0(
#3810
1(
#3820
0(
#3830
1(
#3840
1#
0!
0(
0'
1&
#3850
1(
#3860
0(
#3870
1(
#3880
0(
#3890
1(
#3900
0(
#3910
1(
#3920
0(
#3930
1(
#3940
0(
#3950
1(
#3960
0(
#3970
1(
#3980
0(
#3990
1(
#4000
0(
#4010
1(
#4020
0(
#4030
1(
#4040
0(
#4050
1(
#4060
0(
#4070
1(
#4080
0(
#4090
1(
#4100
0(
#4110
1(
#4120
0(
#4130
1(
#4140
0(
#4150
1(
#4160
1#
b1 *
0(
1'
#4170
1(
#4180
0(
#4190
1(
#4200
0(
#4210
1(
#4220
0(
#4230
1(
#4240
0(
#4250
1(
#4260
0(
#4270
1(
#4280
0(
#4290
1(
#4300
0(
#4310
1(
#4320
0(
#4330
1(
#4340
0(
#4350
1(
#4360
0(
#4370
1(
#4380
0(
#4390
1(
#4400
0(
#4410
1(
#4420
0(
#4430
1(
#4440
0(
#4450
1(
#4460
0(
#4470
1(
#4480
0(
0'
#4490
1(
#4500
0(
#4510
1(
#4520
0(
#4530
1(
#4540
0(
#4550
1(
#4560
0(
#4570
1(
#4580
0(
#4590
1(
#4600
0(
#4610
1(
#4620
0(
#4630
1(
#4640
0(
#4650
1(
#4660
0(
#4670
1(
#4680
0(
#4690
1(
#4700
0(
#4710
1(
#4720
0(
#4730
1(
#4740
0(
#4750
1(
#4760
0(
#4770
1(
#4780
0(
#4790
1(
#4800
1#
b10 *
0(
1'
#4810
1(
#4820
0(
#4830
1(
#4840
0(
#4850
1(
#4860
0(
#4870
1(
#4880
0(
#4890
1(
#4900
0(
#4910
1(
#4920
0(
#4930
1(
#4940
0(
#4950
1(
#4960
0(
#4970
1(
#4980
0(
#4990
1(
#5000
0(
#5010
1(
#5020
0(
#5030
1(
#5040
0(
#5050
1(
#5060
0(
#5070
1(
#5080
0(
#5090
1(
#5100
0(
#5110
1(
#5120
0(
0'
0&
#5130
1(
#5140
0(
#5150
1(
#5160
0(
#5170
1(
#5180
0(
#5190
1(
#5200
0(
#5210
1(
#5220
0(
#5230
1(
#5240
0(
#5250
1(
#5260
0(
#5270
1(
#5280
0(
#5290
1(
#5300
0(
#5310
1(
#5320
0(
#5330
1(
#5340
0(
#5350
1(
#5360
0(
#5370
1(
#5380
0(
#5390
1(
#5400
0(
#5410
1(
#5420
0(
#5430
1(
#5440
1#
b11 *
0(
1'
#5450
1(
#5460
0(
#5470
1(
#5480
0(
#5490
1(
#5500
0(
#5510
1(
#5520
0(
#5530
1(
#5540
0(
#5550
1(
#5560
0(
#5570
1(
#5580
0(
#5590
1(
#5600
0(
#5610
1(
#5620
0(
#5630
1(
#5640
0(
#5650
1(
#5660
0(
#5670
1(
#5680
0(
#5690
1(
#5700
0(
#5710
1(
#5720
0(
#5730
1(
#5740
0(
#5750
1(
#5760
0(
0'
#5770
1(
#5780
0(
#5790
1(
#5800
0(
#5810
1(
#5820
0(
#5830
1(
#5840
0(
#5850
1(
#5860
0(
#5870
1(
#5880
0(
#5890
1(
#5900
0(
#5910
1(
#5920
0(
#5930
1(
#5940
0(
#5950
1(
#5960
0(
#5970
1(
#5980
0(
#5990
1(
#6000
0(
#6010
1(
#6020
0(
#6030
1(
#6040
0(
#6050
1(
#6060
0(
#6070
1(
#6080
1#
b0 *
0(
1'
#6090
1(
#6100
0(
#6110
1(
#6120
0(
#6130
1(
#6140
0(
#6150
1(
#6160
0(
#6170
1(
#6180
0(
#6190
1(
#6200
0(
#6210
1(
#6220
0(
#6230
1(
#6240
0(
#6250
1(
#6260
0(
#6270
1(
#6280
0(
#6290
1(
#6300
0(
#6310
1(
#6320
0(
#6330
1(
#6340
0(
#6350
1(
#6360
0(
#6370
1(
#6380
0(
#6390
1(
#6400
b11111111 "
b11111111 +
b11111111 ,
1#
b11111111111111111111111111111111 $
b11111111111111111111111111111111 )
b11111111111111111111111111111111 -
0(
0'
1&
#6410
1(
#6420
0(
#6430
1(
#6440
0(
#6450
1(
#6460
0(
#6470
1(
#6480
0(
#6490
1(
#6500
0(
#6510
1(
#6520
0(
#6530
1(
#6540
0(
#6550
1(
#6560
0(
#6570
1(
#6580
0(
#6590
1(
#6600
0(
#6610
1(
#6620
0(
#6630
1(
#6640
0(
#6650
1(
#6660
0(
#6670
1(
#6680
0(
#6690
1(
#6700
0(
#6710
1(
#6720
1#
b11111111 "
b11111111 +
b11111111 ,
b1 *
0(
1'
